flowrunner/__init__.py
flowrunner/__main__.py
flowrunner/cli.py
flowrunner/core/__init__.py
flowrunner/core/base.py
flowrunner/core/decorators.py
flowrunner/core/helpers.py
flowrunner/core/templates/__init__.py
flowrunner/core/templates/base.html
flowrunner/core/templates/{{ cookiecutter.project_name }}/.gitignore
flowrunner/core/templates/{{ cookiecutter.project_name }}/changelog.md
flowrunner/core/templates/{{ cookiecutter.project_name }}/pyproject.toml
flowrunner/core/templates/{{ cookiecutter.project_name }}/readme.md
flowrunner/core/templates/{{ cookiecutter.project_name }}/setup.py
flowrunner/core/templates/{{ cookiecutter.project_name }}/{{ cookiecutter.project_slug }}/html_dags/dagsexamplepandas.html
flowrunner/core/templates/{{ cookiecutter.project_name }}/{{ cookiecutter.project_slug }}/my_flows/__init__.py
flowrunner/core/templates/{{ cookiecutter.project_name }}/{{ cookiecutter.project_slug }}/my_flows/pandas_example.py
flowrunner/runner/__init__.py
flowrunner/runner/flow.py
flowrunner/system/__init__.py
flowrunner/system/exceptions.py
flowrunner/system/logger.py
flowrunner-0.2.3.dist-info/LICENSE
flowrunner-0.2.3.dist-info/METADATA
flowrunner-0.2.3.dist-info/WHEEL
flowrunner-0.2.3.dist-info/entry_points.txt
flowrunner-0.2.3.dist-info/top_level.txt
flowrunner-0.2.3.dist-info/RECORD
