Metadata-Version: 2.1
Name: flowrunner
Version: 0.2.3
Summary: Flowrunner is a lightweight package to organize and represent Data Engineering/Science workflows
Author-email: Prithvijit Guha <prithvijit_guha2@hotmail.com>
License: BSD 3-Clause License
Project-URL: Homepage, https://github.com/prithvijitguha/flowrunner
Project-URL: Documentation, https://flowrunner.readthedocs.io/en/latest/
Project-URL: Issues, https://github.com/prithvijitguha/flowrunner/issues
Keywords: Data Engineering,Data Science
Classifier: Operating System :: OS Independent
Classifier: Programming Language :: Python :: 3.8
Classifier: Programming Language :: Python :: 3.9
Classifier: Topic :: Scientific/Engineering
Requires-Python: >=3.8
License-File: LICENSE
Requires-Dist: requests
Requires-Dist: click (>=8.1.3)
Requires-Dist: Jinja2 (>=3.1.2)
Requires-Dist: coloredlogs (>=15.0.1)
Requires-Dist: ipython (>=8.11.0)
Requires-Dist: matplotlib (>=3.7.1)
Requires-Dist: cookiecutter (>=2.1.1)
Requires-Dist: importlib-metadata ; python_version <= "3.8"
Provides-Extra: dev
Requires-Dist: click (>=8.1.3) ; extra == 'dev'
Requires-Dist: Jinja2 (>=3.1.2) ; extra == 'dev'
Requires-Dist: pylint (>=2.16.4) ; extra == 'dev'
Requires-Dist: black (>=23.1.0) ; extra == 'dev'
Requires-Dist: coverage (<=7.2.1) ; extra == 'dev'
Requires-Dist: pytest (>=7.2.1) ; extra == 'dev'
Requires-Dist: pytest-cookies (>=0.7.0) ; extra == 'dev'
Requires-Dist: isort (>=5.12.0) ; extra == 'dev'
Requires-Dist: pre-commit (>=3.1.1) ; extra == 'dev'
Requires-Dist: pandas (>=1.5.3) ; extra == 'dev'
Requires-Dist: ipython (>=8.11.0) ; extra == 'dev'
Requires-Dist: matplotlib (>=3.7.1) ; extra == 'dev'
Requires-Dist: pylint (>=2.17.0) ; extra == 'dev'
Requires-Dist: pyspark (>=3.3.2) ; extra == 'dev'
Requires-Dist: cookiecutter (>=2.1.1) ; extra == 'dev'
Requires-Dist: coloredlogs (<=15.0.1) ; extra == 'dev'
Requires-Dist: ipytest (>=0.13.3) ; extra == 'dev'
Provides-Extra: doc
Requires-Dist: click (>=8.1.3) ; extra == 'doc'
Requires-Dist: Jinja2 (>=3.1.2) ; extra == 'doc'
Requires-Dist: Sphinx (>=6.1.3) ; extra == 'doc'
Requires-Dist: sphinxcontrib-mermaid (>=0.8.1) ; extra == 'doc'
Requires-Dist: sphinx-autoapi (>=2.0.1) ; extra == 'doc'
Requires-Dist: sphinx-tabs (>=3.4.1) ; extra == 'doc'
Requires-Dist: sphinx-autobuild (>=2021.3.14) ; extra == 'doc'
Requires-Dist: sphinx-rtd-theme (>=1.2.0) ; extra == 'doc'
Requires-Dist: isort (>=5.12.0) ; extra == 'doc'
Requires-Dist: black (>=23.1.0) ; extra == 'doc'
Requires-Dist: pre-commit (>=3.1.1) ; extra == 'doc'
Requires-Dist: coverage (<=7.2.1) ; extra == 'doc'
Requires-Dist: pytest (>=7.2.1) ; extra == 'doc'
Requires-Dist: pylint (>=2.17.0) ; extra == 'doc'
Requires-Dist: coloredlogs (<=15.0.1) ; extra == 'doc'
Requires-Dist: ipytest (>=0.13.3) ; extra == 'doc'
Provides-Extra: pandas
Requires-Dist: pandas (>=1.5.3) ; extra == 'pandas'
Provides-Extra: pyspark
Requires-Dist: pyspark (>=3.3.2) ; extra == 'pyspark'
Provides-Extra: test
Requires-Dist: click (>=8.1.3) ; extra == 'test'
Requires-Dist: Jinja2 (>=3.1.2) ; extra == 'test'
Requires-Dist: pytest (>=7.2.1) ; extra == 'test'
Requires-Dist: pytest-cookies (>=0.7.0) ; extra == 'test'
Requires-Dist: black (>=23.1.0) ; extra == 'test'
Requires-Dist: coverage (<=7.2.1) ; extra == 'test'
Requires-Dist: isort (>=5.12.0) ; extra == 'test'
Requires-Dist: pre-commit (>=3.1.1) ; extra == 'test'
Requires-Dist: pandas (>=1.5.3) ; extra == 'test'
Requires-Dist: ipython (>=8.11.0) ; extra == 'test'
Requires-Dist: matplotlib (>=3.7.1) ; extra == 'test'
Requires-Dist: pylint (>=2.17.0) ; extra == 'test'
Requires-Dist: pyspark (>=3.3.2) ; extra == 'test'
Requires-Dist: cookiecutter (>=2.1.1) ; extra == 'test'
Requires-Dist: coloredlogs (<=15.0.1) ; extra == 'test'
Requires-Dist: ipytest (>=0.13.3) ; extra == 'test'
